nesc/__init__.py
nesc/nesc.py
nesc/ai/__init__.py
nesc/ai/seg.py
nesc/apps_fastapi/__init__.py
nesc/apps_fastapi/simapp.py
nesc/apps_fastapi/st_utils.py
nesc/apps_streamlit/__init__.py
nesc/apps_streamlit/_appzoo.py
nesc/apps_streamlit/ai_app.py
nesc/apps_streamlit/apps.py
nesc/apps_streamlit/demo.py
nesc/clis/README.md
nesc/clis/__init__.py
nesc/clis/cli.py
nesc/clis/gui.py
nesc/clis/guis/__init__.py
nesc/clis/guis/ocr.py
nesc/clis/guis/program_icon.png
nesc/clis/guis/seg.py
nesc/clis/guis/test.png
nesc/crawler/WorkBetter(1).py
nesc/crawler/WorkBetter.py
nesc/crawler/WorkBetter22.py
nesc/crawler/WorkMe.py
nesc/crawler/__init__.py
nesc/crawler/demo.py
nesc/dockerfiles/__init__.py
nesc/easydata/__init__.py
nesc/easydata/dask/__init__.py
nesc/easydata/dask/utils.py
nesc/easydata/hive/__init__.py
nesc/easydata/hive/hive.py
nesc/easydata/hive/logger.py
nesc/easydata/hive/utils.py
nesc/easydata/hive/parsers/__init__.py
nesc/easydata/hive/parsers/base_parser.py
nesc/easydata/hive/parsers/orc.py
nesc/easydata/hive/parsers/parquet.py
nesc/easydata/hive/parsers/text.py
nesc/extract/__init__.py
nesc/extract/extract4ddl.py
nesc/extract/extract4excel.py
nesc/extract/hs.py
nesc/gpus/__init__.py
nesc/gpus/catboost_gpu.py
nesc/gpus/tf_gpu.py
nesc/gpus/xgboost_gpu.py
nesc/nescqdata/__init__.py
nesc/nescqdata/_version.py
nesc/nescqdata/baseDataProvider.py
nesc/nescqdata/columnsMap.py
nesc/nescqdata/selfException.py
nesc/nescqdata/utils.py
nesc/nescqdata/BondData/__init__.py
nesc/nescqdata/BondData/dataProvider.py
nesc/nescqdata/FundData/__init__.py
nesc/nescqdata/FundData/dataProvider.py
nesc/nescqdata/FutureData/__init__.py
nesc/nescqdata/MarketData/__init__.py
nesc/nescqdata/MarketData/dataProvider.py
nesc/nescqdata/OptionData/__init__.py
nesc/nescqdata/OptionData/dataProvider.py
nesc/sim/__init__.py
nesc/sim/sim.py
nesc/sim/sim_.py
nesc/sim/simv2.py
nesc/utils/__init__.py
nesc/utils/db_utils.py
nesc/utils/hdfs_utils.py
nesc/utils/s3_utils.py
nesc/word_root/__init__.py
nesc-2023.5.31.10.37.39.dist-info/AUTHORS.rst
nesc-2023.5.31.10.37.39.dist-info/LICENSE
nesc-2023.5.31.10.37.39.dist-info/METADATA
nesc-2023.5.31.10.37.39.dist-info/WHEEL
nesc-2023.5.31.10.37.39.dist-info/entry_points.txt
nesc-2023.5.31.10.37.39.dist-info/top_level.txt
nesc-2023.5.31.10.37.39.dist-info/RECORD
