Metadata-Version: 2.1
Name: nesc
Version: 2023.5.31.10.37.39
Summary: ai for nesc
Home-page: https://github.com/Jie-Yuan/nesc
Author: Betterme
Author-email: yuanjie@example.com
License: MIT license
Keywords: nesc
Classifier: Development Status :: 2 - Pre-Alpha
Classifier: Intended Audience :: Developers
Classifier: License :: OSI Approved :: MIT License
Classifier: Natural Language :: English
Classifier: Programming Language :: Python :: 3
Classifier: Programming Language :: Python :: 3.6
Classifier: Programming Language :: Python :: 3.7
Classifier: Programming Language :: Python :: 3.8
Requires-Python: >=3.6
License-File: LICENSE
License-File: AUTHORS.rst
Requires-Dist: meutils
Requires-Dist: lac
